scMalignantFinder/__init__.py
scMalignantFinder/_version.py
scMalignantFinder/classifier.py
scMalignantFinder/spatial.py
scMalignantFinder/utils.py
scmalignantfinder-1.1.7.dist-info/METADATA
scmalignantfinder-1.1.7.dist-info/WHEEL
scmalignantfinder-1.1.7.dist-info/top_level.txt
scmalignantfinder-1.1.7.dist-info/RECORD
