Metadata-Version: 2.4
Name: scMalignantFinder
Version: 1.1.7
Summary: A tool for identitying malignant cells from single-cell RNA-seq data
Home-page: https://github.com/jonyyqn/scMalignantFinder
Author: Journey Yu
Author-email: jonyyqn@mail.ustc.edu.cn
Requires-Python: >=3.8
Requires-Dist: scanpy==1.9.3
Requires-Dist: anndata==0.9.1
Requires-Dist: scikit-learn==1.2.2
Requires-Dist: pyscenic==0.12.1
Requires-Dist: dask[dataframe]==2024.11.2
Requires-Dist: squidpy==1.3.1
Requires-Dist: numpy<2,>=1.24
Requires-Dist: joblib==1.4.2
Requires-Dist: pandas==2.1.4
Requires-Dist: matplotlib==3.6.3
Requires-Dist: scipy==1.13.1
Requires-Dist: h5py==3.7.0
Dynamic: author
Dynamic: author-email
Dynamic: description
Dynamic: description-content-type
Dynamic: home-page
Dynamic: requires-dist
Dynamic: requires-python
Dynamic: summary
